petu/.gitignore
petu/__init__.py
petu/constants.py
petu/data_handler.py
petu/inferer.py
petu/model_handler.py
petu/utils/__init__.py
petu/utils/citation_reminder.py
petu/weights.py
petu-0.0.7.dist-info/METADATA
petu-0.0.7.dist-info/WHEEL
petu-0.0.7.dist-info/RECORD
