Metadata-Version: 2.4
Name: petu
Version: 0.0.7
Summary: 
Author: Marcel Rosier
Author-email: marcel.rosier@tum.de
Requires-Python: >=3.10,<4.0
Classifier: Programming Language :: Python :: 3
Classifier: Programming Language :: Python :: 3.10
Classifier: Programming Language :: Python :: 3.11
Classifier: Programming Language :: Python :: 3.12
Classifier: Programming Language :: Python :: 3.13
Classifier: Programming Language :: Python :: 3.14
Requires-Dist: blosc2 (>=2.0.0,<3.0.0)
Requires-Dist: connected-components-3d (>=3.23.0,<4.0.0)
Requires-Dist: loguru (>=0.7.3,<0.8.0)
Requires-Dist: nibabel (>=5.3.2,<6.0.0)
Requires-Dist: nnunetv2 (==2.5.2)
Requires-Dist: numpy (>=2.2.2,<3.0.0)
Requires-Dist: rich (>=13.9.4,<14.0.0)
Requires-Dist: torch (>=2.6.0,<3.0.0)
Project-URL: Documentation, https://www.TODO.com
Project-URL: Homepage, https://www.TODO.com
Project-URL: Repository, https://www.TODO.com
